lapizlab/__init__.py
lapizlab/functions.py
lapizlab/preprocessing.py
lapizlab-0.1.0.dist-info/METADATA
lapizlab-0.1.0.dist-info/WHEEL
lapizlab-0.1.0.dist-info/top_level.txt
lapizlab-0.1.0.dist-info/RECORD
