Metadata-Version: 2.1
Name: lapizlab
Version: 0.1.0
Summary: LapizLaboratory
Author: ailapiz
License: AILL
Requires-Dist: numpy
Requires-Dist: pandas
